{"Americas": [{"Country": "Guatemala", "Capital": "Guatemala City", "Flag": "https://flagcdn.com/w320/gt.png"}, {"Country": "Panama", "Capital": "Panama City", "Flag": "https://flagcdn.com/w320/pa.png"}, {"Country": "Nicaragua", "Capital": "Managua", "Flag": "https://flagcdn.com/w320/ni.png"}, {"Country": "Barbados", "Capital": "Bridgetown", "Flag": "https://flagcdn.com/w320/bb.png"}, {"Country": "Cuba", "Capital": "Havana", "Flag": "https://flagcdn.com/w320/cu.png"}, {"Country": "Costa Rica", "Capital": "San Jos\u00e9", "Flag": "https://flagcdn.com/w320/cr.png"}, {"Country": "El Salvador", "Capital": "San Salvador", "Flag": "https://flagcdn.com/w320/sv.png"}, {"Country": "Honduras", "Capital": "Tegucigalpa", "Flag": "https://flagcdn.com/w320/hn.png"}, {"Country": "Trinidad and Tobago", "Capital": "Port of Spain", "Flag": "https://flagcdn.com/w320/tt.png"}, {"Country": "United States", "Capital": "Washington, D.C.", "Flag": "https://flagcdn.com/w320/us.png"}, {"Country": "Argentina", "Capital": "Buenos Aires", "Flag": "https://flagcdn.com/w320/ar.png"}, {"Country": "Chile", "Capital": "Santiago", "Flag": "https://flagcdn.com/w320/cl.png"}, {"Country": "Uruguay", "Capital": "Montevideo", "Flag": "https://flagcdn.com/w320/uy.png"}, {"Country": "Canada", "Capital": "Ottawa", "Flag": "https://flagcdn.com/w320/ca.png"}, {"Country": "Peru", "Capital": "Lima", "Flag": "https://flagcdn.com/w320/pe.png"}, {"Country": "Haiti", "Capital": "Port-au-Prince", "Flag": "https://flagcdn.com/w320/ht.png"}, {"Country": "Mexico", "Capital": "Mexico City", "Flag": "https://flagcdn.com/w320/mx.png"}, {"Country": "Saint Kitts and Nevis", "Capital": "Basseterre", "Flag": "https://flagcdn.com/w320/kn.png"}, {"Country": "Dominica", "Capital": "Roseau", "Flag": "https://flagcdn.com/w320/dm.png"}, {"Country": "Bolivia", "Capital": "Sucre", "Flag": "https://flagcdn.com/w320/bo.png"}, {"Country": "Dominican Republic", "Capital": "Santo Domingo", "Flag": "https://flagcdn.com/w320/do.png"}, {"Country": "Grenada", "Capital": "St. George's", "Flag": "https://flagcdn.com/w320/gd.png"}, {"Country": "Jamaica", "Capital": "Kingston", "Flag": "https://flagcdn.com/w320/jm.png"}, {"Country": "Antigua and Barbuda", "Capital": "Saint John's", "Flag": "https://flagcdn.com/w320/ag.png"}, {"Country": "Belize", "Capital": "Belmopan", "Flag": "https://flagcdn.com/w320/bz.png"}, {"Country": "Colombia", "Capital": "Bogot\u00e1", "Flag": "https://flagcdn.com/w320/co.png"}, {"Country": "Paraguay", "Capital": "Asunci\u00f3n", "Flag": "https://flagcdn.com/w320/py.png"}, {"Country": "Saint Lucia", "Capital": "Castries", "Flag": "https://flagcdn.com/w320/lc.png"}, {"Country": "Ecuador", "Capital": "Quito", "Flag": "https://flagcdn.com/w320/ec.png"}, {"Country": "Saint Vincent and the Grenadines", "Capital": "Kingstown", "Flag": "https://flagcdn.com/w320/vc.png"}, {"Country": "Brazil", "Capital": "Bras\u00edlia", "Flag": "https://flagcdn.com/w320/br.png"}, {"Country": "Guyana", "Capital": "Georgetown", "Flag": "https://flagcdn.com/w320/gy.png"}, {"Country": "Venezuela", "Capital": "Caracas", "Flag": "https://flagcdn.com/w320/ve.png"}, {"Country": "Suriname", "Capital": "Paramaribo", "Flag": "https://flagcdn.com/w320/sr.png"}, {"Country": "Bahamas", "Capital": "Nassau", "Flag": "https://flagcdn.com/w320/bs.png"}], "Asia": [{"Country": "Singapore", "Capital": "Singapore", "Flag": "https://flagcdn.com/w320/sg.png"}, {"Country": "Maldives", "Capital": "Mal\u00e9", "Flag": "https://flagcdn.com/w320/mv.png"}, {"Country": "Jordan", "Capital": "Amman", "Flag": "https://flagcdn.com/w320/jo.png"}, {"Country": "Bangladesh", "Capital": "Dhaka", "Flag": "https://flagcdn.com/w320/bd.png"}, {"Country": "Bhutan", "Capital": "Thimphu", "Flag": "https://flagcdn.com/w320/bt.png"}, {"Country": "India", "Capital": "New Delhi", "Flag": "https://flagcdn.com/w320/in.png"}, {"Country": "Cambodia", "Capital": "Phnom Penh", "Flag": "https://flagcdn.com/w320/kh.png"}, {"Country": "Israel", "Capital": "Jerusalem", "Flag": "https://flagcdn.com/w320/il.png"}, {"Country": "Turkey", "Capital": "Ankara", "Flag": "https://flagcdn.com/w320/tr.png"}, {"Country": "Myanmar", "Capital": "Naypyidaw", "Flag": "https://flagcdn.com/w320/mm.png"}, {"Country": "Lebanon", "Capital": "Beirut", "Flag": "https://flagcdn.com/w320/lb.png"}, {"Country": "Philippines", "Capital": "Manila", "Flag": "https://flagcdn.com/w320/ph.png"}, {"Country": "Kazakhstan", "Capital": "Nur-Sultan", "Flag": "https://flagcdn.com/w320/kz.png"}, {"Country": "Tajikistan", "Capital": "Dushanbe", "Flag": "https://flagcdn.com/w320/tj.png"}, {"Country": "Azerbaijan", "Capital": "Baku", "Flag": "https://flagcdn.com/w320/az.png"}, {"Country": "Afghanistan", "Capital": "Kabul", "Flag": "https://upload.wikimedia.org/wikipedia/commons/thumb/5/5c/Flag_of_the_Taliban.svg/320px-Flag_of_the_Taliban.svg.png"}, {"Country": "Qatar", "Capital": "Doha", "Flag": "https://flagcdn.com/w320/qa.png"}, {"Country": "Yemen", "Capital": "Sana'a", "Flag": "https://flagcdn.com/w320/ye.png"}, {"Country": "Iran", "Capital": "Tehran", "Flag": "https://flagcdn.com/w320/ir.png"}, {"Country": "Syria", "Capital": "Damascus", "Flag": "https://flagcdn.com/w320/sy.png"}, {"Country": "North Korea", "Capital": "Pyongyang", "Flag": "https://flagcdn.com/w320/kp.png"}, {"Country": "Bahrain", "Capital": "Manama", "Flag": "https://flagcdn.com/w320/bh.png"}, {"Country": "Georgia", "Capital": "Tbilisi", "Flag": "https://flagcdn.com/w320/ge.png"}, {"Country": "Mongolia", "Capital": "Ulan Bator", "Flag": "https://flagcdn.com/w320/mn.png"}, {"Country": "Indonesia", "Capital": "Jakarta", "Flag": "https://flagcdn.com/w320/id.png"}, {"Country": "Armenia", "Capital": "Yerevan", "Flag": "https://flagcdn.com/w320/am.png"}, {"Country": "United Arab Emirates", "Capital": "Abu Dhabi", "Flag": "https://flagcdn.com/w320/ae.png"}, {"Country": "Pakistan", "Capital": "Islamabad", "Flag": "https://flagcdn.com/w320/pk.png"}, {"Country": "Turkmenistan", "Capital": "Ashgabat", "Flag": "https://flagcdn.com/w320/tm.png"}, {"Country": "Brunei", "Capital": "Bandar Seri Begawan", "Flag": "https://flagcdn.com/w320/bn.png"}, {"Country": "Kuwait", "Capital": "Kuwait City", "Flag": "https://flagcdn.com/w320/kw.png"}, {"Country": "Saudi Arabia", "Capital": "Riyadh", "Flag": "https://flagcdn.com/w320/sa.png"}, {"Country": "Malaysia", "Capital": "Kuala Lumpur", "Flag": "https://flagcdn.com/w320/my.png"}, {"Country": "Nepal", "Capital": "Kathmandu", "Flag": "https://flagcdn.com/w320/np.png"}, {"Country": "Kyrgyzstan", "Capital": "Bishkek", "Flag": "https://flagcdn.com/w320/kg.png"}, {"Country": "Timor-Leste", "Capital": "Dili", "Flag": "https://flagcdn.com/w320/tl.png"}, {"Country": "Vietnam", "Capital": "Hanoi", "Flag": "https://flagcdn.com/w320/vn.png"}, {"Country": "Japan", "Capital": "Tokyo", "Flag": "https://flagcdn.com/w320/jp.png"}, {"Country": "China", "Capital": "Beijing", "Flag": "https://flagcdn.com/w320/cn.png"}, {"Country": "Laos", "Capital": "Vientiane", "Flag": "https://flagcdn.com/w320/la.png"}, {"Country": "Iraq", "Capital": "Baghdad", "Flag": "https://flagcdn.com/w320/iq.png"}, {"Country": "Thailand", "Capital": "Bangkok", "Flag": "https://flagcdn.com/w320/th.png"}, {"Country": "Uzbekistan", "Capital": "Tashkent", "Flag": "https://flagcdn.com/w320/uz.png"}, {"Country": "Sri Lanka", "Capital": "Sri Jayawardenepura Kotte", "Flag": "https://flagcdn.com/w320/lk.png"}, {"Country": "South Korea", "Capital": "Seoul", "Flag": "https://flagcdn.com/w320/kr.png"}, {"Country": "Oman", "Capital": "Muscat", "Flag": "https://flagcdn.com/w320/om.png"}], "Europe": [{"Country": "Bosnia and Herzegovina", "Capital": "Sarajevo", "Flag": "https://flagcdn.com/w320/ba.png"}, {"Country": "Latvia", "Capital": "Riga", "Flag": "https://flagcdn.com/w320/lv.png"}, {"Country": "Greece", "Capital": "Athens", "Flag": "https://flagcdn.com/w320/gr.png"}, {"Country": "Italy", "Capital": "Rome", "Flag": "https://flagcdn.com/w320/it.png"}, {"Country": "France", "Capital": "Paris", "Flag": "https://flagcdn.com/w320/fr.png"}, {"Country": "Norway", "Capital": "Oslo", "Flag": "https://flagcdn.com/w320/no.png"}, {"Country": "San Marino", "Capital": "City of San Marino", "Flag": "https://flagcdn.com/w320/sm.png"}, {"Country": "Netherlands", "Capital": "Amsterdam", "Flag": "https://flagcdn.com/w320/nl.png"}, {"Country": "Russia", "Capital": "Moscow", "Flag": "https://flagcdn.com/w320/ru.png"}, {"Country": "Slovenia", "Capital": "Ljubljana", "Flag": "https://flagcdn.com/w320/si.png"}, {"Country": "Portugal", "Capital": "Lisbon", "Flag": "https://flagcdn.com/w320/pt.png"}, {"Country": "Croatia", "Capital": "Zagreb", "Flag": "https://flagcdn.com/w320/hr.png"}, {"Country": "Romania", "Capital": "Bucharest", "Flag": "https://flagcdn.com/w320/ro.png"}, {"Country": "Cyprus", "Capital": "Nicosia", "Flag": "https://flagcdn.com/w320/cy.png"}, {"Country": "Bulgaria", "Capital": "Sofia", "Flag": "https://flagcdn.com/w320/bg.png"}, {"Country": "North Macedonia", "Capital": "Skopje", "Flag": "https://flagcdn.com/w320/mk.png"}, {"Country": "Spain", "Capital": "Madrid", "Flag": "https://flagcdn.com/w320/es.png"}, {"Country": "Sweden", "Capital": "Stockholm", "Flag": "https://flagcdn.com/w320/se.png"}, {"Country": "Liechtenstein", "Capital": "Vaduz", "Flag": "https://flagcdn.com/w320/li.png"}, {"Country": "Ukraine", "Capital": "Kyiv", "Flag": "https://flagcdn.com/w320/ua.png"}, {"Country": "Poland", "Capital": "Warsaw", "Flag": "https://flagcdn.com/w320/pl.png"}, {"Country": "Luxembourg", "Capital": "Luxembourg", "Flag": "https://flagcdn.com/w320/lu.png"}, {"Country": "Iceland", "Capital": "Reykjavik", "Flag": "https://flagcdn.com/w320/is.png"}, {"Country": "Lithuania", "Capital": "Vilnius", "Flag": "https://flagcdn.com/w320/lt.png"}, {"Country": "Serbia", "Capital": "Belgrade", "Flag": "https://flagcdn.com/w320/rs.png"}, {"Country": "Moldova", "Capital": "Chi\u0219in\u0103u", "Flag": "https://flagcdn.com/w320/md.png"}, {"Country": "Belarus", "Capital": "Minsk", "Flag": "https://flagcdn.com/w320/by.png"}, {"Country": "Malta", "Capital": "Valletta", "Flag": "https://flagcdn.com/w320/mt.png"}, {"Country": "Albania", "Capital": "Tirana", "Flag": "https://flagcdn.com/w320/al.png"}, {"Country": "Andorra", "Capital": "Andorra la Vella", "Flag": "https://flagcdn.com/w320/ad.png"}, {"Country": "Czechia", "Capital": "Prague", "Flag": "https://flagcdn.com/w320/cz.png"}, {"Country": "Vatican City", "Capital": "Vatican City", "Flag": "https://flagcdn.com/w320/va.png"}, {"Country": "Estonia", "Capital": "Tallinn", "Flag": "https://flagcdn.com/w320/ee.png"}, {"Country": "Austria", "Capital": "Vienna", "Flag": "https://flagcdn.com/w320/at.png"}, {"Country": "United Kingdom", "Capital": "London", "Flag": "https://flagcdn.com/w320/gb.png"}, {"Country": "Ireland", "Capital": "Dublin", "Flag": "https://flagcdn.com/w320/ie.png"}, {"Country": "Finland", "Capital": "Helsinki", "Flag": "https://flagcdn.com/w320/fi.png"}, {"Country": "Montenegro", "Capital": "Podgorica", "Flag": "https://flagcdn.com/w320/me.png"}, {"Country": "Slovakia", "Capital": "Bratislava", "Flag": "https://flagcdn.com/w320/sk.png"}, {"Country": "Monaco", "Capital": "Monaco", "Flag": "https://flagcdn.com/w320/mc.png"}, {"Country": "Hungary", "Capital": "Budapest", "Flag": "https://flagcdn.com/w320/hu.png"}, {"Country": "Germany", "Capital": "Berlin", "Flag": "https://flagcdn.com/w320/de.png"}, {"Country": "Switzerland", "Capital": "Bern", "Flag": "https://flagcdn.com/w320/ch.png"}, {"Country": "Belgium", "Capital": "Brussels", "Flag": "https://flagcdn.com/w320/be.png"}, {"Country": "Denmark", "Capital": "Copenhagen", "Flag": "https://flagcdn.com/w320/dk.png"}], "Africa": [{"Country": "Algeria", "Capital": "Algiers", "Flag": "https://flagcdn.com/w320/dz.png"}, {"Country": "S\u00e3o Tom\u00e9 and Pr\u00edncipe", "Capital": "S\u00e3o Tom\u00e9", "Flag": "https://flagcdn.com/w320/st.png"}, {"Country": "Gabon", "Capital": "Libreville", "Flag": "https://flagcdn.com/w320/ga.png"}, {"Country": "Mauritius", "Capital": "Port Louis", "Flag": "https://flagcdn.com/w320/mu.png"}, {"Country": "DR Congo", "Capital": "Kinshasa", "Flag": "https://flagcdn.com/w320/cd.png"}, {"Country": "Sierra Leone", "Capital": "Freetown", "Flag": "https://flagcdn.com/w320/sl.png"}, {"Country": "Rwanda", "Capital": "Kigali", "Flag": "https://flagcdn.com/w320/rw.png"}, {"Country": "Mozambique", "Capital": "Maputo", "Flag": "https://flagcdn.com/w320/mz.png"}, {"Country": "Nigeria", "Capital": "Abuja", "Flag": "https://flagcdn.com/w320/ng.png"}, {"Country": "Gambia", "Capital": "Banjul", "Flag": "https://flagcdn.com/w320/gm.png"}, {"Country": "Egypt", "Capital": "Cairo", "Flag": "https://flagcdn.com/w320/eg.png"}, {"Country": "Kenya", "Capital": "Nairobi", "Flag": "https://flagcdn.com/w320/ke.png"}, {"Country": "Equatorial Guinea", "Capital": "Malabo", "Flag": "https://flagcdn.com/w320/gq.png"}, {"Country": "Cape Verde", "Capital": "Praia", "Flag": "https://flagcdn.com/w320/cv.png"}, {"Country": "Botswana", "Capital": "Gaborone", "Flag": "https://flagcdn.com/w320/bw.png"}, {"Country": "Mauritania", "Capital": "Nouakchott", "Flag": "https://flagcdn.com/w320/mr.png"}, {"Country": "Somalia", "Capital": "Mogadishu", "Flag": "https://flagcdn.com/w320/so.png"}, {"Country": "Morocco", "Capital": "Rabat", "Flag": "https://flagcdn.com/w320/ma.png"}, {"Country": "Madagascar", "Capital": "Antananarivo", "Flag": "https://flagcdn.com/w320/mg.png"}, {"Country": "Chad", "Capital": "N'Djamena", "Flag": "https://flagcdn.com/w320/td.png"}, {"Country": "Eswatini", "Capital": "Mbabane", "Flag": "https://flagcdn.com/w320/sz.png"}, {"Country": "Djibouti", "Capital": "Djibouti", "Flag": "https://flagcdn.com/w320/dj.png"}, {"Country": "Guinea", "Capital": "Conakry", "Flag": "https://flagcdn.com/w320/gn.png"}, {"Country": "Central African Republic", "Capital": "Bangui", "Flag": "https://flagcdn.com/w320/cf.png"}, {"Country": "Mali", "Capital": "Bamako", "Flag": "https://flagcdn.com/w320/ml.png"}, {"Country": "Ethiopia", "Capital": "Addis Ababa", "Flag": "https://flagcdn.com/w320/et.png"}, {"Country": "Libya", "Capital": "Tripoli", "Flag": "https://flagcdn.com/w320/ly.png"}, {"Country": "Namibia", "Capital": "Windhoek", "Flag": "https://flagcdn.com/w320/na.png"}, {"Country": "Republic of the Congo", "Capital": "Brazzaville", "Flag": "https://flagcdn.com/w320/cg.png"}, {"Country": "Liberia", "Capital": "Monrovia", "Flag": "https://flagcdn.com/w320/lr.png"}, {"Country": "South Africa", "Capital": "Pretoria", "Flag": "https://flagcdn.com/w320/za.png"}, {"Country": "Togo", "Capital": "Lom\u00e9", "Flag": "https://flagcdn.com/w320/tg.png"}, {"Country": "South Sudan", "Capital": "Juba", "Flag": "https://flagcdn.com/w320/ss.png"}, {"Country": "Cameroon", "Capital": "Yaound\u00e9", "Flag": "https://flagcdn.com/w320/cm.png"}, {"Country": "Comoros", "Capital": "Moroni", "Flag": "https://flagcdn.com/w320/km.png"}, {"Country": "Ghana", "Capital": "Accra", "Flag": "https://flagcdn.com/w320/gh.png"}, {"Country": "Eritrea", "Capital": "Asmara", "Flag": "https://flagcdn.com/w320/er.png"}, {"Country": "Zimbabwe", "Capital": "Harare", "Flag": "https://flagcdn.com/w320/zw.png"}, {"Country": "Tanzania", "Capital": "Dodoma", "Flag": "https://flagcdn.com/w320/tz.png"}, {"Country": "Uganda", "Capital": "Kampala", "Flag": "https://flagcdn.com/w320/ug.png"}, {"Country": "Zambia", "Capital": "Lusaka", "Flag": "https://flagcdn.com/w320/zm.png"}, {"Country": "Tunisia", "Capital": "Tunis", "Flag": "https://flagcdn.com/w320/tn.png"}, {"Country": "Burundi", "Capital": "Gitega", "Flag": "https://flagcdn.com/w320/bi.png"}, {"Country": "Benin", "Capital": "Porto-Novo", "Flag": "https://flagcdn.com/w320/bj.png"}, {"Country": "Sudan", "Capital": "Khartoum", "Flag": "https://flagcdn.com/w320/sd.png"}, {"Country": "Burkina Faso", "Capital": "Ouagadougou", "Flag": "https://flagcdn.com/w320/bf.png"}, {"Country": "Niger", "Capital": "Niamey", "Flag": "https://flagcdn.com/w320/ne.png"}, {"Country": "Angola", "Capital": "Luanda", "Flag": "https://flagcdn.com/w320/ao.png"}, {"Country": "Ivory Coast", "Capital": "Yamoussoukro", "Flag": "https://flagcdn.com/w320/ci.png"}, {"Country": "Lesotho", "Capital": "Maseru", "Flag": "https://flagcdn.com/w320/ls.png"}, {"Country": "Malawi", "Capital": "Lilongwe", "Flag": "https://flagcdn.com/w320/mw.png"}, {"Country": "Seychelles", "Capital": "Victoria", "Flag": "https://flagcdn.com/w320/sc.png"}, {"Country": "Senegal", "Capital": "Dakar", "Flag": "https://flagcdn.com/w320/sn.png"}], "Oceania": [{"Country": "Nauru", "Capital": "Yaren", "Flag": "https://flagcdn.com/w320/nr.png"}, {"Country": "Tuvalu", "Capital": "Funafuti", "Flag": "https://flagcdn.com/w320/tv.png"}, {"Country": "Marshall Islands", "Capital": "Majuro", "Flag": "https://flagcdn.com/w320/mh.png"}, {"Country": "Papua New Guinea", "Capital": "Port Moresby", "Flag": "https://flagcdn.com/w320/pg.png"}, {"Country": "Vanuatu", "Capital": "Port Vila", "Flag": "https://flagcdn.com/w320/vu.png"}, {"Country": "Palau", "Capital": "Ngerulmud", "Flag": "https://flagcdn.com/w320/pw.png"}, {"Country": "Fiji", "Capital": "Suva", "Flag": "https://flagcdn.com/w320/fj.png"}, {"Country": "Solomon Islands", "Capital": "Honiara", "Flag": "https://flagcdn.com/w320/sb.png"}, {"Country": "New Zealand", "Capital": "Wellington", "Flag": "https://flagcdn.com/w320/nz.png"}, {"Country": "Samoa", "Capital": "Apia", "Flag": "https://flagcdn.com/w320/ws.png"}, {"Country": "Australia", "Capital": "Canberra", "Flag": "https://flagcdn.com/w320/au.png"}, {"Country": "Tonga", "Capital": "Nuku'alofa", "Flag": "https://flagcdn.com/w320/to.png"}, {"Country": "Kiribati", "Capital": "South Tarawa", "Flag": "https://flagcdn.com/w320/ki.png"}, {"Country": "Micronesia", "Capital": "Palikir", "Flag": "https://flagcdn.com/w320/fm.png"}]}